setup.py
blended_google_fonts.egg-info/PKG-INFO
blended_google_fonts.egg-info/SOURCES.txt
blended_google_fonts.egg-info/dependency_links.txt
blended_google_fonts.egg-info/not-zip-safe
blended_google_fonts.egg-info/requires.txt
blended_google_fonts.egg-info/top_level.txt
google_fonts/__init__.py