Metadata-Version: 1.0
Name: blended-google-fonts
Version: 1.0
Summary: Easy Google Fonts import for Blended
Home-page: http://jmroper.com/blended/
Author: John Roper
Author-email: johnroper100@gmail.com
License: GPL3.0
Platform: UNKNOWN
